quantum_dot_sim/__init__.py
quantum_dot_sim/config.py
quantum_dot_sim/custom_exceptions.py
quantum_dot_sim/data_loader.py
quantum_dot_sim/energy_levels.py
quantum_dot_sim/interactive_mode.py
quantum_dot_sim/ml_energy_levels.py
quantum_dot_sim/quantum_array.py
quantum_dot_sim/quantum_simulation.py
quantum_dot_sim/sketch.py
quantum_dot_sim/spectra.py
quantum_dot_sim/utils.py
quantum_dot_sim/visualization.py
quantum_dot_sim/wavefunctions.py
quantum_dot_sim-2.1.1.dist-info/LICENSE.txt
quantum_dot_sim-2.1.1.dist-info/METADATA
quantum_dot_sim-2.1.1.dist-info/WHEEL
quantum_dot_sim-2.1.1.dist-info/entry_points.txt
quantum_dot_sim-2.1.1.dist-info/top_level.txt
quantum_dot_sim-2.1.1.dist-info/RECORD
