Metadata-Version: 2.2
Name: quantum_dot_sim
Version: 2.1.1
Summary: A package for simulating quantum dot behavior and analyzing energy levels, absorption spectra, and wavefunctions
Home-page: https://github.com/ArjunSkanda/quantum_dot_sim
Author: Arjun Skanda Ananda
Author-email: arjunskanda@yahoo.com
License: MIT
Classifier: License :: OSI Approved :: MIT License
Classifier: Operating System :: OS Independent
Classifier: Programming Language :: Python :: 3
Classifier: Programming Language :: Python :: 3.7
Classifier: Programming Language :: Python :: 3.8
Classifier: Programming Language :: Python :: 3.9
Classifier: Programming Language :: Python :: 3.10
Classifier: Programming Language :: Python :: 3.11
Requires-Python: >=3.7,<3.11
License-File: LICENSE.txt
Requires-Dist: numpy<2.1.0,>=1.22.0
Requires-Dist: PyOpenGL==3.1.7
Requires-Dist: PyOpenGL-accelerate==3.1.7
Requires-Dist: scipy==1.14.1
Requires-Dist: matplotlib==3.10.0
Requires-Dist: pandas==2.2.3
Requires-Dist: pygame==2.6.1
Requires-Dist: tensorflow==2.18.0
Requires-Dist: tensorflow-io-gcs-filesystem==0.31.0
Requires-Dist: keras==3.7.0
Requires-Dist: scikit-learn==1.6.0
Requires-Dist: tensorboard==2.18.0
Requires-Dist: tensorboard-data-server==0.7.2
Requires-Dist: shap==0.46.0
Requires-Dist: numba==0.60.0
Requires-Dist: absl-py==2.1.0
Requires-Dist: astunparse==1.6.3
Requires-Dist: cloudpickle==3.1.0
Requires-Dist: contourpy==1.3.1
Requires-Dist: cycler==0.12.1
Requires-Dist: flatbuffers==24.3.25
Requires-Dist: fonttools==4.55.3
Requires-Dist: gast==0.4.0
Requires-Dist: google-pasta==0.2.0
Requires-Dist: grpcio==1.68.1
Requires-Dist: h5py==3.12.1
Requires-Dist: joblib==1.4.2
Requires-Dist: kiwisolver==1.4.7
Requires-Dist: libclang==18.1.1
Requires-Dist: llvmlite==0.43.0
Requires-Dist: ml-dtypes==0.4.1
Requires-Dist: opt_einsum==3.4.0
Requires-Dist: optree==0.13.1
Requires-Dist: packaging==24.2
Requires-Dist: protobuf==3.20.3
Requires-Dist: six==1.17.0
Requires-Dist: slicer==0.0.8
Requires-Dist: termcolor==2.5.0
Requires-Dist: threadpoolctl==3.5.0
Requires-Dist: typing_extensions==4.12.2
Requires-Dist: wrapt==1.17.0
Requires-Dist: Markdown==3.7
Requires-Dist: Pygments==2.18.0
Requires-Dist: rich==13.9.4
Requires-Dist: docutils==0.21.2
Requires-Dist: colorama==0.4.6
Requires-Dist: pytz==2024.2
Requires-Dist: tzdata==2024.2
Requires-Dist: urllib3==2.2.3
Requires-Dist: Werkzeug==3.1.3
Requires-Dist: zipp==3.21.0
Requires-Dist: pywin32-ctypes==0.2.3
Requires-Dist: backports.tarfile==1.2.0
Dynamic: author
Dynamic: author-email
Dynamic: classifier
Dynamic: description
Dynamic: description-content-type
Dynamic: home-page
Dynamic: license
Dynamic: requires-dist
Dynamic: requires-python
Dynamic: summary
